Mshpy/BSaMP.py
Mshpy/Msh_Nstep_3D.py
Mshpy/Msh_Nstep_Romashets.py
Mshpy/Msh_Nstep_SMILE.py
Mshpy/Msh_Nstep_SMILE_fig.py
Mshpy/Msh_Nstep_Soucek.py
Mshpy/Msh_Nstep_Soucek_backup.py
Mshpy/Msh_Nstep_Soucek_backup2.py
Mshpy/Msh_Nstep_Spreiter.py
Mshpy/Msh_Nstep_Spreiter_restructure.py
Mshpy/Msh_Nstep_Spreiter_scatter.py
Mshpy/Msh_Nstep_Spreiter_scatter_nv.py
Mshpy/Msh_Nstep_Spreiter_test.py
Mshpy/Msh_Nstep_THEMIS_comb.py
Mshpy/Msh_Nstep_comp.py
Mshpy/Msh_Nstep_comp2.py
Mshpy/Msh_Nstep_comp_rad.py
Mshpy/Msh_Nstep_comp_rad_0.1.py
Mshpy/Msh_Nstep_comp_rad_0.1_MPBS.py
Mshpy/Msh_Nstep_comp_rad_cs.py
Mshpy/Msh_Nstep_interp.py
Mshpy/Msh_Nstep_master.py
Mshpy/Msh_Nstep_master_backup.py
Mshpy/Msh_Nstep_orbit.py
Mshpy/Msh_Nstep_restructure.py
Mshpy/Msh_Nstep_restructure_n.py
Mshpy/Msh_Nstep_scatter.py
Mshpy/Msh_Nstep_scatter_0.1.py
Mshpy/Msh_Nstep_scatter_0.1_temp_test.py
Mshpy/Msh_Nstep_scatter_density.py
Mshpy/Msh_Nstep_temp_test.py
Mshpy/Msh_Nstep_temp_test_scatter.py
Mshpy/Msh_Nstep_test.py
Mshpy/Msh_Nstep_test_n.py
Mshpy/Msh_cusp_plot.py
Mshpy/Msh_cusp_restructure.py
Mshpy/Msh_sc_data.py
Mshpy/__init__.py
Mshpy/conf.py
Mshpy/easyplot.py
Mshpy/event_info.py
Mshpy/get_GEdata.py
Mshpy/get_THdata.py
Mshpy/get_scorbit.py
Mshpy/jrmod01.py
Mshpy/mhd_plot_cut.py
Mshpy/omni.py
Mshpy/openggcm_info.py
Mshpy/paper_info.py
Mshpy/pkg_mhdplot.py
Mshpy/pkg_rates.py
Mshpy/plot_rates.py
Mshpy/plot_rates2.py
Mshpy/read_2DMHD.py
Mshpy/read_mhd.py
Mshpy/read_rates.py
Mshpy/read_sc.py
Mshpy/run_info.py
Mshpy/sc_data.py
Mshpy/sc_orbit_plot.py
Mshpy/sscweb.py
Mshpy/swdata.py
Mshpy/timehist_info.py
Mshpy/xray_cut_Msh.py
Mshpy/xraysc_sight_Msh.py
Mshpy/data/init
Mshpy/data/Spreiter/Msh_T
Mshpy/data/Spreiter/Msh_V
Mshpy/data/Spreiter/Msh_n
mshpy-0.1.3.dist-info/licenses/LICENSE
mshpy-0.1.3.dist-info/METADATA
mshpy-0.1.3.dist-info/WHEEL
mshpy-0.1.3.dist-info/top_level.txt
mshpy-0.1.3.dist-info/RECORD
