Metadata-Version: 2.4
Name: Mshpy
Version: 0.1.3
Summary: Simplified Earth magnetosheath model
License-File: LICENSE
Requires-Dist: sympy
Dynamic: description
Dynamic: description-content-type
Dynamic: license-file
Dynamic: requires-dist
Dynamic: summary
